shap_bootstrap/__init__.py
shap_bootstrap/building_blocks.py
shap_bootstrap/cluster.py
shap_bootstrap/custom_pipeline.py
shap_bootstrap/datasets.py
shap_bootstrap/metrics.py
shap_bootstrap/models.py
shap_bootstrap/utils.py
shap_bootstrap/visualisation.py
shap_bootstrap/data/AB_NYC_2019.csv
shap_bootstrap/data/Admission_Predict.csv
shap_bootstrap/data/Fish.csv
shap_bootstrap/data/amazon.csv
shap_bootstrap/data/insurance.csv
shap_bootstrap/data/stats_import_data.csv
shap_bootstrap/data/student-mat.csv
shap_bootstrap/static/branch8-pipeline2.png
shap_bootstrap/static/global-overview.png
shap_bootstrap/static/pred_scatter.png
shap_bootstrap/static/shap-summary-plot.png
shap_bootstrap-0.0.13.dist-info/LICENSE
shap_bootstrap-0.0.13.dist-info/METADATA
shap_bootstrap-0.0.13.dist-info/WHEEL
shap_bootstrap-0.0.13.dist-info/top_level.txt
shap_bootstrap-0.0.13.dist-info/RECORD
